pylgmath/__init__.py
pylgmath/common/__init__.py
pylgmath/common/operations.py
pylgmath/se3/__init__.py
pylgmath/se3/operations.py
pylgmath/se3/transformation.py
pylgmath/se3/transformation_with_covariance.py
pylgmath/so3/__init__.py
pylgmath/so3/operations.py
pylgmath/so3/rotation.py
asrl_pylgmath-1.0.3.dist-info/LICENSE
asrl_pylgmath-1.0.3.dist-info/METADATA
asrl_pylgmath-1.0.3.dist-info/WHEEL
asrl_pylgmath-1.0.3.dist-info/top_level.txt
asrl_pylgmath-1.0.3.dist-info/RECORD
