Metadata-Version: 2.1
Name: asrl-pylgmath
Version: 1.0.3
Summary: Python implementation of lgmath
Home-page: https://github.com/utiasASRL/pylgmath
Author: Yuchen Wu
Author-email: cheney.wu@mail.utoronto.ca
License: BSD
Platform: UNKNOWN
Requires-Python: >=3.8
Requires-Dist: numpy (>=1.21.0)
Requires-Dist: scipy (>=1.7.0)
